{
"3cbib5zrmxnjxa7pkvj6vm5r":["1uppodcast","1UP Podcast"],
"jffhmq3etihjjsqjlnermqos":["3upper","3UP"],
"dgf467kto5o4g7dt5qpk5qvl":["1uppixelz","Pixel🍑(/ω＼)"],
"wbamlnywr5qqzawdrpzu53gd":["aggressiverack","Uppity Nerf"],
"fg5z3fduuguezf5b5qcyyfre":["ashwinexe","Ashwin Kumar Uppala"],
"tjxv265xsysujkm7ibxygpvr":["carltonupp","Carlton Upperdine"],
"ddk6iqyw5kcuhysqamqg725t":"cant-uppercut",
"fn44cm4uqbouhty2yv27o6am":["chipstisdag","uppseendeväckande promemoria"],
"6wxzvr5ktrhsnxzazsqat7m7":["clintmeatwood","Unapologetic Uppity Negro "],
"3fs534d5hs3n37gsawnznit5":["cyber.lol","UpperCenter 🏳️‍⚧️"],
"uxbl435expawzu5w7f5sbghx":["dovalore","dove @ setting things upp"],
"2cc7wosvur5lrhlqx4d5jp77":["elinhansson","DJ Upptagetton"],
"mrubstwracxe2ah26lyw7btc":["hansuppenkamp","Hans Uppenkamp "],
"ftmewi4e54jfgdyk2f2w4sy6":["iamuppsala","Uppsala ʕ•ᴥ•ʔ"],
"6nsclasdetd5ckqh3sufzj7k":["jasdeepuppal","Jasdeep Uppal"],
"kua42ugsbplcxxtt6u6hskag":["katyupperman","Katy Upperman"],
"ze7pfjty7bw4s2gkyufsthln":["liv3itup","Liv3itUpp.xx"],
"ljahlf6fqho6rs2yd2yxkyeo":["madinflation","Upper Bavaria Cyclist "],
"iflu2vl2pf4bi62vocb2ireo":["miriable","Miriable, the Quicker Picker-Upper"],
"bmiwtb4zle6ucghlm2fkr7tw":["percocet","Jayson Uppal"],
"4cewad42cvnntwk4nujme7q5":["robotalgore","The \"IMF\" of the upper midwest"],
"jheh7k2wvifxpftdlv6p5xgr":["s0upper","웩숫물"],
"cs6snpcbq46h4m5ncub2v6er":["silverstarpuppy","🅱️ig 🅱️uppy "],
"3w2hay5nghlbl3umfizumofg":["thumbsupping","ThumbsUpping"],
"cnppis5qkfaiubcivgvjvloc":["tupper6261","Tim Upper"],
"cqygauductbftnq7mjz7qk7x":["ucdp","Uppsala Conflict Data Program"],
"y2hmprrzzwvrpivkjuppwiry":["ues99","Uppereastsider"],
"55bdbazrmlaqkarfqkzkro27":["uppityokie","Lynn from OK"],
"c4v44z2afaq7kizfdai7hwzy":["uppgefin","beinahrúga í húðsekk"],
"d66uw7dki2iyodk44dpauo5r":["uppertiersteve","Steve F"],
"eck43r2hdhcptrqe7ppurifu":["uppercayce","Linked Out (Cayce)"],
"ffwrzabmkgmusfrwqorztpvr":["uppy86","Uppy"],
"3tdj4uwmrnxh7uvhuts6stmb":["upperbeech","Upperbeech"],
"2py3gykp6dvlg4hizeczlv3o":["uppercut","Uppercut"],
"ktv7ntvd6uzw7hi4n557uwtf":["uppercaseccc","Chris"],
"6oqw3ffw4t3fdezh3o7frfir":["upperechilon","MattyJ"],
"twtd2acoejm4lry56w3juw5c":["upperchambersnob","Ami "],
"nxt5qb3r74jjz3y2fyzgdqan":"upperthighs",
"4tsqdvx5qjypcphvjwwjmnmb":["uppityalice","AlicePalace"],
"yvrmgiyfdlqdwzk4p4u7sis5":["uppercase","kɐce."],
"agzqrhxrygbjzd5yesnrq5bz":["uppermindink","✎𝕵𝖚𝖘𝖙𝖔𝖓⚔️✨"],
"iqjw3soiwry4ecrd4444a7bx":"upper50",
"5l2wl3y22xgp3qlef2l6p7gn":["upperlimit13","NT-liveLO"],
"vf5t6ljvgcwi3jnahlrzhpdh":["uppitywoman","UppityWoman"],
"j7f7m6xf6c2ahqpm6w5hfllq":["uppvfx","UPP VFX"],
"wommij6mjha6f4gq2m3yalxt":["uppityducky","Ducky🐤✨🫧VTUBER"],
"gmkzqizgq53mc2bx54wjv744":["uppitycrow","Jim Henson's Folk Horror Baby"],
"dtsza4uuo44fhlfwjghbcrkj":["uppy1129","うっぴー"],
"nnhv6wfxy7zmr3hhqzfnue45":["upperton","Andy Upperton"],
"qq6von47y7mst3icznpmdbmg":["uppili","Uppili Ventures"],
"thswnbvigdya6ynv6375b3dl":"uppalmaurya",
"2po45gcjfzjilvxmlasji2xe":"uppityoz",
"gtxtsleaijrqll2ovrcft77s":"uppityhillbilly",
"n3go5ulhsrp373p3ga3rydrb":["upperstories","Isabelle Austin"],
"amwys23uax7iw25jb2bfs6jb":["upper","upper"],
"vwbppgyuk3v4fei25cwlqfbc":["upperblackeddypa","DavidTaylor"],
"se4uzlyjxck4luwffpmyewiv":["uppahalds","Uppáhalds"],
"iccgtncndnxp55aqdtzhacaq":"upperpeninsula",
"s3opor3wiepidw73fljmh33o":["uppun","어펀 Uppun"],
"oykfyyefxuru3k5z5eukqdtw":"upper90clubpod",
"yimkflgjxk3x5654uz44y54e":"uppityinsomniac",
"7mr33zuykvoidym4dbzfjmhf":["upperbeck","Beck"],
"652r27imesvhonvqbelvqyga":["upperkase93","Kase"],
"5flw4crgbn4xm3jmb43ttpig":["uppitywomyn","UppityWomyn"],
"7smijwdcy4atummpjfvswjaj":"upp19femton",
"ycy4ef4hxgdzuh7zpgosv523":"uppenberg",
"g3ifandvmub5wmdnkvnqh72x":"upperroots",
"hqp3opqw2v7zkv36ko2v7mef":"upp",
"nm3l7gyjatexz4ls3uunjugq":"uppergg",
"ggfbdutzkithus3rokidwx7v":["uppafari","Uppafari"],
"pgsiannohvsga7dhgbqncbyj":"uppviglare",
"fqlq5gdo46g2nhti5vnxbtmz":["uppsnerjd","suss 💫"],
"3tuu7ee4ohffsf5ptqqiundy":"uppslammad",
"534x6wxzretelz34naq2w4gm":"uppercanyon",
"4gtvxdqbbgwhhmx7lrechehs":"upperfalls",
"ysemo2o46fzkjqorl67e26x2":["utterlysour","uppersking "],
"wybjzzqlw6ehdla2qx4qzizt":["uwsgay20","Upper West Side Gay"]
}
