{
"o6iefcz5srcdaw5nwqca7bza":["astrobellatrix","Tanya Urrutia"],
"yrxsgzpbewfx53urrsjcywk2":["aurrutia","A.Urrutia"],
"sk3eykwii3znloyuwmrb4hfc":["bpu77","Brian Urrutia"],
"eaawsbzurmslk2fxcxspoyhk":"bri-urrito",
"ba4fb2sxcliqefjxgkibjweh":["carlosurriza","Carlos Martín Urriza"],
"frk3e6oxcd2aqtvlat7z3n7b":["dorisurrutia","Doris Urrutia"],
"mg55vqxdum7ondicgt7bxw2m":["doniaurraca","Doña Urraca "],
"snx6xnlyc3ix4jdgbdarlz3g":["escritorasdeurras","Las Escritoras de Urras"],
"b434qj7zkl6lfuni7lzvtkqy":["heatherurry","Heather Urry"],
"g2echl35ealuv3zem4ooxyjj":["iurgiurrutia","iurgi urrutia "],
"4ecghppn4lgz3xiwisjto4my":["jorgeurreta","Jorge Urreta"],
"3njk2o2nobii4ay7pbdaufz6":["pelutsuotz","Jon Sebasten Urrutia | Pelut"],
"kjek2rjehlelbsib3ir7i7m3":["realsteveurry","Steve Urry"],
"uwrg7tqbxj36bwugr6tggyon":["saladusa","Sal Urrea"],
"fvzd2u22yfjs2wxjmdvvpqry":["splinterfright","Urri en las trincheras de la cultura pop."],
"rsznpjdy22mph32xiqpvktsm":["taufiqurrahman","Taufiq'urrahman"],
"lnapyutsv7oqkztkzps3skel":["uaisa","Raisa Urribarri"],
"fc3fpijifk6r4g7m5ggp6p33":["urrosewood","로즈우드"],
"jioy2bwxpqti46hvul7kletg":["urrealism","Luis Alberto Urrea (& Cindy!)"],
"of5f4w6enb6c5nisokeqaavu":["urrutia","JP"],
"tnhzla6te3o5frhfih53rw2g":["urrealworldaway","Колискова для кота"],
"adpsduqskmgqndfizrcqddan":["urraccoongf","Racc"],
"pokqjtl6eq3wirghva354eir":["urrsso","urso"],
"7gwupwdvxbrvlunn7eaogxus":["urruenjoyer","Mystic Appreciator"],
"ptjwgwnitwm37ixscd2fqosd":["urrrasti","Sale bête "],
"jojhu6rxwqfanavyk2jj2obn":["urracas","Lau 🌿"],
"762vndtxeffsfv6k7pu7acsd":"urrk",
"x6gzmy5lp7zjnoyxmvk5jbig":["urrestarazu","Inigo Urrestarazu-Porta"],
"hxfrzep2juju6ydzhnmsgnz6":"urraca",
"ajxgzhy65bqpgrogsdibhx3t":"urrutiahugo",
"5kbwinkddiqdvztvgwp2bfcj":["urrid","Carsten Caspers"],
"q6v3on67fosttp2hu2bpklqr":["urracacoja","urracacoja"],
"o3pub5wgd2ihjidjc5anqcbf":["urrito","Urrito el perro pistolas"],
"yhtlfe7d3xdyg4sziaea5mt2":["urrmeli","urrmeli"],
"bxbn7u65ykl7tdrufheolqny":["urrunofthemillsjw","Re"],
"u7pyiimnwh3oh6iamiasqvfi":"urre",
"dl4hu4oxscu2ll2kfjpkhl5g":["urriauzkost","Urria Úzkost"],
"op7hh3vjiuw3j6e4q5m5hazl":["urrila","Penna Urrila"],
"jetiwqg3qvsorwlt64mzrzqt":"urri",
"yevpjargrswyqi5nmamg2v6c":["varzim05","Filipe Urriça "]
}
